eval_framework/__init__.py
eval_framework/base_config.py
eval_framework/context/__init__.py
eval_framework/context/determined.py
eval_framework/context/eval.py
eval_framework/context/local.py
eval_framework/evaluation_generator.py
eval_framework/exceptions.py
eval_framework/external/ifeval_impl/README.md
eval_framework/external/ifeval_impl/instructions.py
eval_framework/external/ifeval_impl/instructions_registry.py
eval_framework/external/ifeval_impl/instructions_util.py
eval_framework/external/ifeval_impl/utils.py
eval_framework/llm/__init__.py
eval_framework/llm/aleph_alpha.py
eval_framework/llm/base.py
eval_framework/llm/huggingface.py
eval_framework/llm/mistral.py
eval_framework/llm/models.py
eval_framework/llm/openai.py
eval_framework/llm/vllm.py
eval_framework/logger.py
eval_framework/main.py
eval_framework/metrics/__init__.py
eval_framework/metrics/base.py
eval_framework/metrics/completion/__init__.py
eval_framework/metrics/completion/accuracy_completion.py
eval_framework/metrics/completion/aidanbench.py
eval_framework/metrics/completion/bleu.py
eval_framework/metrics/completion/chrf.py
eval_framework/metrics/completion/code_assertion.py
eval_framework/metrics/completion/code_execution_pass_at_one.py
eval_framework/metrics/completion/comet.py
eval_framework/metrics/completion/concordance_index.py
eval_framework/metrics/completion/csv_format.py
eval_framework/metrics/completion/cwe_accuracy.py
eval_framework/metrics/completion/exponential_similarity.py
eval_framework/metrics/completion/f1.py
eval_framework/metrics/completion/format_checker.py
eval_framework/metrics/completion/grid_difference.py
eval_framework/metrics/completion/ifeval.py
eval_framework/metrics/completion/json_format.py
eval_framework/metrics/completion/language_checker.py
eval_framework/metrics/completion/length_control.py
eval_framework/metrics/completion/math_reasoning_completion.py
eval_framework/metrics/completion/niah_accuracy.py
eval_framework/metrics/completion/placeholder_checker.py
eval_framework-0.2.11.dist-info/WHEEL
eval_framework-0.2.11.dist-info/entry_points.txt
eval_framework-0.2.11.dist-info/METADATA
eval_framework-0.2.11.dist-info/RECORD
