Metadata-Version: 2.3
Name: eval-framework
Version: 0.2.11
Summary: Evalulation Framework
Author: Aleph Alpha Research
License:                                  Apache License
Classifier: Operating System :: OS Independent
Classifier: License :: OSI Approved :: Apache Software License
Classifier: Programming Language :: Python
Classifier: Programming Language :: Python :: 3.12
Classifier: Programming Language :: Python :: 3 :: Only
Classifier: Topic :: Software Development :: Libraries
Classifier: Typing :: Typed
Requires-Dist: pyyaml>=6.0.1,<7
Requires-Dist: xmltodict>=0.13.0,<0.16
Requires-Dist: pydantic>=2.7,<3
Requires-Dist: datasets>=2.19.1,<4
Requires-Dist: sacrebleu>=2.4.3,<3
Requires-Dist: pycountry>=24.6.1,<25
Requires-Dist: nltk>=3.9.1,<4
Requires-Dist: python-dotenv>=1.0.1,<2
Requires-Dist: lingua-language-detector>=2.0.2,<3
Requires-Dist: google-crc32c>=1.5.0,<2
Requires-Dist: kubernetes>=31.0.0,<32
Requires-Dist: langdetect>=1.0.9,<2
Requires-Dist: spacy>=3.8.3,<4
Requires-Dist: jsonschema>=4.23.0,<5
Requires-Dist: mysql-connector-python>=9.0.0,<10
Requires-Dist: psycopg2-binary>=2.9.9,<3
Requires-Dist: sympy>=1.13.1,<2
Requires-Dist: llm-sandbox[docker]>=0.1.8,<0.2
Requires-Dist: jsonlines>=4,<5
Requires-Dist: lxml>=6,<7
Requires-Dist: python-iso639>=2025.2.18
Requires-Dist: wandb>=0.23.0,<1
Requires-Dist: boto3>=1.40.54,<2
Requires-Dist: numpy>=1.26.4
Requires-Dist: antlr4-python3-runtime==4.11.0
Requires-Dist: accelerate ; extra == 'accelerate'
Requires-Dist: eval-framework[determined,api,openai,transformers,accelerate,vllm,comet,optional,mistral] ; extra == 'all'
Requires-Dist: aleph-alpha-client>=11.5.1 ; extra == 'api'
Requires-Dist: unbabel-comet>=2.2.6,<3 ; extra == 'comet'
Requires-Dist: determined>=0.38,<0.39 ; extra == 'determined'
Requires-Dist: tensorboard==2.19.0 ; extra == 'determined'
Requires-Dist: mistral-common>=1.7,<2 ; extra == 'mistral'
Requires-Dist: huggingface-hub>=0.33.2,<0.34 ; extra == 'mistral'
Requires-Dist: eval-framework[vllm] ; extra == 'mistral'
Requires-Dist: openai>=1.62,<2.8 ; extra == 'openai'
Requires-Dist: tiktoken>=0.9,<0.10 ; extra == 'openai'
Requires-Dist: transformers>=4.45.2,<5 ; extra == 'openai'
Requires-Dist: transformers>=4.45.2,<5 ; extra == 'optional'
Requires-Dist: jinja2>=3.1.6,<4 ; extra == 'optional'
Requires-Dist: transformers>=4.45.2,<5 ; extra == 'transformers'
Requires-Dist: torch>=2.5,<3 ; extra == 'transformers'
Requires-Dist: accelerate>=0.30.0,<1 ; extra == 'transformers'
Requires-Dist: vllm>=0.8.5,<0.9 ; extra == 'vllm'
Requires-Dist: torch>=2.5,<3 ; extra == 'vllm'
Requires-Python: >=3.12, <3.13
Project-URL: repository, https://github.com/Aleph-Alpha-Research/eval-framework
Provides-Extra: accelerate
Provides-Extra: all
Provides-Extra: api
Provides-Extra: comet
Provides-Extra: determined
Provides-Extra: mistral
Provides-Extra: openai
Provides-Extra: optional
Provides-Extra: transformers
Provides-Extra: vllm
